bcgs/__init__.py
bcgs/bcgs.py
bcgs-0.2.0.dist-info/LICENSE
bcgs-0.2.0.dist-info/METADATA
bcgs-0.2.0.dist-info/WHEEL
bcgs-0.2.0.dist-info/top_level.txt
bcgs-0.2.0.dist-info/RECORD
