Metadata-Version: 2.1
Name: bcgs
Version: 0.2.0
Summary: Bayesian Conjugate Gibbs Sampler
Home-page: https://github.com/abmantz/bcgs
Author: Adam Mantz
Author-email: amantz@slac.stanford.edu
License: BSD 3-Clause
Classifier: Development Status :: 4 - Beta
Classifier: Intended Audience :: Education
Classifier: License :: OSI Approved :: BSD License
Classifier: Programming Language :: Python :: 3
License-File: LICENSE
Requires-Dist: numpy
Requires-Dist: scipy
